pydemic_ui/__init__.py
pydemic_ui/examples.py
pydemic_ui/i18n.py
pydemic_ui/info.py
pydemic_ui/runner.py
pydemic_ui/apps/__init__.py
pydemic_ui/apps/calc.py
pydemic_ui/apps/projections.py
pydemic_ui/apps/projections_br.py
pydemic_ui/assets/custom.html
pydemic_ui/assets/footnote_disclaimer.en_US.md
pydemic_ui/assets/footnote_disclaimer.pt_BR.md
pydemic_ui/assets/icon.svg
pydemic_ui/assets/css-components/carousel.css
pydemic_ui/assets/css-components/collapse.css
pydemic_ui/assets/css-components/dropdown.css
pydemic_ui/assets/css-components/modal.css
pydemic_ui/assets/css-components/tab.css
pydemic_ui/assets/css-components/tooltip.css
pydemic_ui/components/__init__.py
pydemic_ui/components/base.py
pydemic_ui/components/charts.py
pydemic_ui/components/generic.py
pydemic_ui/components/pyplot.py
pydemic_ui/components/ui.py
pydemic_ui/components/input/__init__.py
pydemic_ui/components/input/epidemiological_params.py
pydemic_ui/components/input/select_intervention.py
pydemic_ui/components/input/select_region.py
pydemic_ui/components/input/simulation_params.py
pydemic_ui/locale/messages.pot
pydemic_ui/locale/pt_BR/LC_MESSAGES/messages.po
pydemic_ui/pyplot/__init__.py
pydemic_ui/pyplot/helpers.py
pydemic_ui/pyplot/pydemic.py
pydemic_ui/st/__init__.py
pydemic_ui/st/conf.py
pydemic_ui/st/sidebar.py
pydemic_ui/ui/__init__.py
pydemic_ui/ui/output_charts.py
pydemic_ui/ui/output_components.py
pydemic_ui/ui/ui_accessor.py
pydemic_ui-0.1.0.dist-info/LICENSE
pydemic_ui-0.1.0.dist-info/WHEEL
pydemic_ui-0.1.0.dist-info/METADATA
pydemic_ui-0.1.0.dist-info/RECORD
